Metadata-Version: 2.1
Name: vectara-skunk-client
Version: 0.5.11
Summary: Vectara Skunk Client
Home-page: https://github.com/davidglevy/vectara-skunk-client
Author: David Levy
Author-email: david.g.levy@gmail.com
License: GNU AFFERO GENERAL PUBLIC LICENSE v3
Classifier: Development Status :: 2 - Pre-Alpha
Classifier: Environment :: Console
Classifier: License :: OSI Approved :: GNU Affero General Public License v3 or later (AGPLv3+)
Classifier: Natural Language :: English
Classifier: Programming Language :: Python :: 3 :: Only
Classifier: Programming Language :: Python :: 3.12
Classifier: Topic :: Utilities
Requires-Python: >=3.4
License-File: LICENSE.md
Requires-Dist: requests
Requires-Dist: dacite >=1.8.1
Requires-Dist: Authlib ==1.3.1
Requires-Dist: pyaml ==23.9.7
Requires-Dist: tqdm ==4.66.1
Requires-Dist: requests-toolbelt ==1.0.0
Requires-Dist: cryptography ==40.0.2
